cms_detector/__init__.py
cms_detector-0.0.1.dist-info/LICENSE
cms_detector-0.0.1.dist-info/METADATA
cms_detector-0.0.1.dist-info/WHEEL
cms_detector-0.0.1.dist-info/top_level.txt
cms_detector-0.0.1.dist-info/RECORD
